ridescanapi/__init__.py
ridescanapi/client.py
ridescanapi/exceptions.py
ridescanapi-1.4.0.dist-info/METADATA
ridescanapi-1.4.0.dist-info/WHEEL
ridescanapi-1.4.0.dist-info/top_level.txt
ridescanapi-1.4.0.dist-info/RECORD
