Metadata-Version: 2.4
Name: ridescanapi
Version: 1.4.0
Summary: Official Python SDK for the RideScan Safety Layer API
Author-email: RideScan Engineering <support@ridescan.ai>
License-Expression: MIT
Classifier: Programming Language :: Python :: 3
Classifier: Operating System :: OS Independent
Requires-Python: >=3.7
Requires-Dist: requests>=2.25.0
